{
  "encrypt": {
    "with-extension": "", 
    "output": "examples/dist", 
    "runflag": 1, 
    "path": "", 
    "args": "examples/beer.py", 
    "with-capsule": "examples/foo.zip"
  }, 
  "license": {
    "bind": 0, 
    "expired-date": "2016-03-25", 
    "filename": "", 
    "with-capsule": "examples/foo.zip", 
    "output": "examples/dist", 
    "args": "MYPROJECT-001", 
    "runflag": 1
  }, 
  "capsule": {
    "filename": "examples/foo.zip", 
    "key": "", 
    "output": "", 
    "args": "", 
    "runflag": 0
  }
}