[
  {
    "_id": "000000010000010001e64c00",
    "name": "Top",
    "description": "All system wide settings, users, permissions, rights ",
    "createdWhen": "2014-11-13T01:00:00+00:00",
    "schemaId": "a9ca8030-6ea4-11e4-9803-0800200c9a66",
    "canRead": ["000000010000010001e64c28"],
    "canWrite": ["000000010000010001e64c28"],
    "allowedChildTypes": ["a9ca8030-6ea4-11e4-9803-0800200c9a66"]
  },
  {
    "_id": "000000010000010001e64c23",
    "parent_id": "000000010000010001e64c00",
    "name": "Administration",
    "description": "All system wide settings, users, permissions, rights ",
    "createdWhen": "2014-11-13T01:00:00+00:00",
    "schemaId": "a9ca8030-6ea4-11e4-9803-0800200c9a66",
    "canRead": ["000000010000010001e64c28"],
    "canWrite": ["000000010000010001e64c28"],
    "allowedChildTypes": ["a9ca8030-6ea4-11e4-9803-0800200c9a66"]
  },
  {
    "_id": "000000010000010001e64c24",
    "parent_id": "000000010000010001e64c23",
    "name": "Groups",
    "description": "All groups and their settings",
    "createdWhen": "2014-11-13T01:00:00+00:00",
    "schemaId": "a9ca8030-6ea4-11e4-9803-0800200c9a66",
    "canRead": ["000000010000010001e64c28"],
    "canWrite": ["000000010000010001e64c28"],
    "allowedChildTypes": ["5d3b8e21-adf3-4005-b73c-1fb63a46f399"]
  },
  {
    "_id": "000000010000010001e64c25",
    "parent_id": "000000010000010001e64c23",
    "name": "Users",
    "description": "All users and their settings",
    "createdWhen": "2014-11-13T01:00:00+00:00",
    "schemaId": "a9ca8030-6ea4-11e4-9803-0800200c9a66",
    "canRead": ["000000010000010001e64c28"],
    "canWrite": ["000000010000010001e64c28"],
    "allowedChildTypes": ["2fb3b2c9-a29c-4fc0-b29d-6eed738b6dab"]
  },
  {
    "_id": "000000010000010001e64c26",
    "parent_id": "000000010000010001e64c23",
    "name": "Rights",
    "description": "All the defined rights and their settings",
    "createdWhen": "2014-11-13T01:00:00+00:00",
    "schemaId": "a9ca8030-6ea4-11e4-9803-0800200c9a66",
    "canRead": ["000000010000010001e64c28"],
    "canWrite": ["000000010000010001e64c28"],
    "allowedChildTypes": ["4288fc06-d615-4f1c-ac10-8328153f2c54"]
  },
  {
    "_id": "000000010000010001e64c27",
    "parent_id": "000000010000010001e64c26",
    "name": "Administer everything",
    "description": "The Administer everything right",
    "createdWhen": "2014-11-13T01:00:00+00:00",
    "schemaId": "4288fc06-d615-4f1c-ac10-8328153f2c54",
    "canRead": ["000000010000010001e64c28"],
    "canWrite": ["000000010000010001e64c28"],
    "allowedChildTypes": []
  },
  {
    "_id": "000000010000010001e64c28",
    "parent_id": "000000010000010001e64c24",
    "name": "Administrators",
    "createdWhen": "2014-11-13T01:00:00+00:00",
    "schemaId": "5d3b8e21-adf3-4005-b73c-1fb63a46f399",
    "rights": ["000000010000010001e64c27"],
    "canRead": ["000000010000010001e64c28"],
    "canWrite": ["000000010000010001e64c28"],
    "allowedChildTypes": []
  },
  {
    "_id": "000000010000010001e64c29",
    "parent_id": "000000010000010001e64c24",
    "name": "Users",
    "description": "The users group",
    "createdWhen": "2014-11-13T01:00:00+00:00",
    "schemaId": "5d3b8e21-adf3-4005-b73c-1fb63a46f399",
    "rights": [],
    "canRead": ["000000010000010001e64c28"],
    "canWrite": ["000000010000010001e64c28"],
    "allowedChildTypes": []
  },
  {
    "_id": "000000010000010001e64c30",
    "parent_id": "000000010000010001e64c25",
    "name": "root",
    "credentials": {
      "usernamePassword": {
        "username": "root",
        "password": "63a9f0ea7bb98050796b649e85481845"
      }
    },
    "createdWhen": "2014-11-13T01:00:00+00:00",
    "schemaId": "2fb3b2c9-a29c-4fc0-b29d-6eed738b6dab",
    "groups": ["000000010000010001e64c28"],
    "canRead": ["000000010000010001e64c28"],
    "canWrite": ["000000010000010001e64c28"],
    "allowedChildTypes": []
  }
]